Workbook

Sheet Cover
B2: ADANI PORTS & SEZ LTD (APSEZ)
B3: Discounted Cash Flow Valuation Model | NSE: ADANIPORTS
B6: Analyst | C6: Aayush Garg
B7: Model Date | C7: May 2026
B8: Currency | C8: INR (₹ Crores)
B9: Fiscal Year End | C9: March 31
B10: Ticker | C10: ADANIPORTS | BSE: 532921
B11: Data Source | C11: Screener.in, BSE Filings, Annual Reports
B14: Model Overview
B15: Cover | C15: Model overview and navigation
B16: Assumptions | C16: WACC, growth rates, and key drivers
B17: Income Stmt | C17: Historical P&L (FY20–FY25)
B18: DCF | C18: 5-year FCF projection + terminal value + valuation
B19: Sensitivity | C19: WACC × TGR sensitivity table on implied share price
B22: Color Key
B23: ■ | C23: Blue — Hardcoded inputs (change these for scenarios)
B24: ■ | C24: Black — Formulas / calculated values
B25: ■ | C25: Green — Cross-sheet links
B26: ■ | C26: Red — External data sources

Sheet Assumptions
A1: WACC ASSUMPTIONS
A2: Risk-Free Rate (10Y G-Sec) | B2: 0.0718 | C2: Source: RBI, May 2026
A3: Equity Risk Premium (India) | B3: 0.06 | C3: Source: Damodaran, Jan 2026
A4: Beta (5Y Monthly vs Nifty 50) | B4: 0.85 | C4: Source: NSE / Screener.in
A5: Cost of Equity [RFR + β×ERP] | B5: =B2+B4*B3 -> 0.1228
A6: Pre-tax Cost of Debt | B6: 0.0785 | C6: Source: APSEZ Bonds / CRISIL AA
A7: Tax Rate | B7: 0.15 | C7: Source: FY24-25 avg effective rate
A8: After-tax Cost of Debt | B8: =B6*(1-B7) -> 0.066725
A9: Market Cap (₹ Cr) | B9: 309674 | C9: Source: NSE, May 2026
A10: Total Debt (₹ Cr) | B10: 51621 | C10: Source: Balance Sheet Mar-25
A11: Weight of Equity | B11: =B9/(B9+B10) -> 0.8571223
A12: Weight of Debt | B12: =B10/(B9+B10) -> 0.1428777
A13: WACC | B13: =B11*B5+B12*B8 -> 0.11478813
A15: PROJECTION ASSUMPTIONS (FY26E–FY30E)
A16: Revenue Growth — Ports Segment | B16: 0.14 | C16: Mgmt guidance ~400 MMT by FY28; ~14% CAGR
A17: Revenue Growth — Logistics | B17: 0.18 | C17: Rail + MMLP ramp; management guidance
A18: Blended Revenue Growth (yr 1-3) | B18: =0.6*B16+0.4*B17 -> 0.156
A19: Revenue Growth (yr 4-5) | B19: 0.12 | C19: Tapering to long-run India GDP+
A20: EBITDA Margin | B20: 0.6 | C20: Source: FY25 actual 60%; held flat
A21: D&A % of Revenue | B21: 0.143 | C21: Source: FY25 D&A/Rev avg
A22: CapEx % of Revenue | B22: 0.22 | C22: Infra-heavy; mgmt capex ₹6,500 Cr/yr avg
A23: Change in Working Capital % Rev | B23: -0.03 | C23: Negative WC = cash inflow; hist avg
A24: Terminal Growth Rate | B24: 0.055 | C24: India nominal GDP growth long-run
A25: Shares Outstanding (Cr) | B25: 216 | C25: Source: NSE Mar-25
A26: Cash & Equivalents (₹ Cr) | B26: 4659 | C26: Source: Balance Sheet Mar-25
A27: Total Debt (₹ Cr) | B27: 51621 | C27: Source: Balance Sheet Mar-25
A28: Minority Interest (₹ Cr) | B28: 8500 | C28: Estimated from consol. financials

Sheet Income Stmt
A1: ADANI PORTS & SEZ — CONSOLIDATED P&L (₹ Crores)
B2: FY20 | C2: FY21 | D2: FY22 | E2: FY23 | F2: FY24 | G2: FY25
A3: Revenue (₹ Cr) | B3: 11873 | C3: 12550 | D3: 17119 | E3: 20852 | F3: 26711 | G3: 30475
A4: % Growth | C4: 0.057 | D4: 0.364 | E4: 0.219 | F4: 0.281 | G4: 0.141
A5: Operating Expenses | B5: 5926 | C5: 3862 | D5: 7591 | E5: 9905 | F5: 11121 | G5: 12335
A6: EBITDA | B6: 5947 | C6: 8688 | D6: 9528 | E6: 10947 | F6: 15589 | G6: 18141
A7: EBITDA Margin | B7: =B6/B3 -> 0.50088436 | C7: =C6/C3 -> 0.69227092 | D7: =D6/D3 -> 0.55657457 | E7: =E6/E3 -> 0.52498561 | F7: =F6/F3 -> 0.58361724 | G7: =G6/G3 -> 0.59527482
A8: Depreciation & Amort. | B8: 1680 | C8: 2107 | D8: 3099 | E8: 3425 | F8: 3888 | G8: 4379
A9: EBIT | B9: 4267 | C9: 6581 | D9: 6429 | E9: 7522 | F9: 11701 | G9: 13762
A10: EBIT Margin | B10: =B9/B3 -> 0.35938684 | C10: =C9/C3 -> 0.52438247 | D10: =D9/D3 -> 0.37554764 | E10: =E9/E3 -> 0.36073278 | F10: =F9/F3 -> 0.43805923 | G10: =G9/G3 -> 0.45158326
A11: Interest Expense | B11: 1951 | C11: 2255 | D11: 2544 | E11: 2363 | F11: 2733 | G11: 2532
A12: Other Income | B12: 1928 | C12: 1967 | D12: 1832 | E12: 327 | F12: 671 | G12: 1800
A13: PBT | B13: 4244 | C13: 6292 | D13: 5717 | E13: 5487 | F13: 9639 | G13: 13030
A14: Tax | B14: 459 | C14: 1243 | D14: 764 | E14: 96 | F14: 1535 | G14: 1969
A15: Net Profit | B15: 3785 | C15: 5049 | D15: 4953 | E15: 5391 | F15: 8104 | G15: 11061
A16: Net Margin | B16: =B15/B3 -> 0.31879053 | C16: =C15/C3 -> 0.40231076 | D16: =D15/D3 -> 0.28932765 | E16: =E15/E3 -> 0.25853635 | F16: =F15/F3 -> 0.3033956 | G16: =G15/G3 -> 0.36295324
A18: KEY METRICS
B19: FY20 | C19: FY21 | D19: FY22 | E19: FY23 | F19: FY24 | G19: FY25
A20: EPS (₹) | B20: 18.52 | C20: 24.58 | D20: 23.13 | E20: 24.58 | F20: 37.55 | G20: 51.35
A21: ROCE % | B21: 0.12 | C21: 0.14 | D21: 0.11 | E21: 0.1 | F21: 0.13 | G21: 0.14
A22: ROE % | B22: 0.15 | C22: 0.18 | D22: 0.13 | E22: 0.13 | F22: 0.18 | G22: 0.19
A23: Debt/EBITDA | B23: 5.1 | C23: 4.1 | D23: 5 | E23: 4.9 | F23: 3.2 | G23: 2.8

Sheet DCF
A1: REVENUE & EBITDA BUILD (₹ Crores)
B2: FY25A | C2: FY26E | D2: FY27E | E2: FY28E | F2: FY29E | G2: FY30E
A3: Revenue (₹ Cr) | B3: ='Income Stmt'!G3 -> 30475 | C3: =B3*(1+Assumptions!B18) -> 35229.1 | D3: =C3*(1+Assumptions!B18) -> 40724.84 | E3: =D3*(1+Assumptions!B18) -> 47077.915 | F3: =E3*(1+Assumptions!B19) -> 52727.264 | G3: =F3*(1+Assumptions!B19) -> 59054.536
A4: % Growth | C4: =(C3-B3)/B3 -> 0.156 | D4: =(D3-C3)/C3 -> 0.156 | E4: =(E3-D3)/D3 -> 0.156 | F4: =(F3-E3)/E3 -> 0.12 | G4: =(G3-F3)/F3 -> 0.12
A5: EBITDA | B5: ='Income Stmt'!G6 -> 18141 | C5: =C3*Assumptions!B20 -> 21137.46 | D5: =D3*Assumptions!B20 -> 24434.904 | E5: =E3*Assumptions!B20 -> 28246.749 | F5: =F3*Assumptions!B20 -> 31636.359 | G5: =G3*Assumptions!B20 -> 35432.722 | I5: CORRECTED: was =Income Stmt!G9 (EBIT). Now correctly references EBITDA (G6). [Error 3]
A6: EBITDA Margin | B6: =B5/B3 -> 0.59527482 | C6: =C5/C3 -> 0.6 | D6: =D5/D3 -> 0.6 | E6: =E5/E3 -> 0.6 | F6: =F5/F3 -> 0.6 | G6: =G5/G3 -> 0.6
A7: Depreciation & Amort. | B7: ='Income Stmt'!G8 -> 4379 | C7: =C3*Assumptions!B21 -> 5037.7613 | D7: =D3*Assumptions!B21 -> 5823.6521 | E7: =E3*Assumptions!B21 -> 6732.1418 | F7: =F3*Assumptions!B21 -> 7539.9988 | G7: =G3*Assumptions!B21 -> 8444.7987 | I7: CORRECTED: was =Income Stmt!G11 (Interest Expense). Now correctly references D&A (G8). [Error 2]
A8: EBIT | B8: =B5-B7 -> 13762 | C8: =C5-C7 -> 16099.699 | D8: =D5-D7 -> 18611.252 | E8: =E5-E7 -> 21514.607 | F8: =F5-F7 -> 24096.36 | G8: =G5-G7 -> 26987.923
A9: Taxes on EBIT | B9: =B8*Assumptions!B7 -> 2064.3 | C9: =C8*Assumptions!B7 -> 2414.9548 | D9: =D8*Assumptions!B7 -> 2791.6878 | E9: =E8*Assumptions!B7 -> 3227.191 | F9: =F8*Assumptions!B7 -> 3614.454 | G9: =G8*Assumptions!B7 -> 4048.1884
A10: EBIAT (EBIT after tax) | B10: =B8-B9 -> 11697.7 | C10: =C8-C9 -> 13684.744 | D10: =D8-D9 -> 15819.564 | E10: =E8-E9 -> 18287.416 | F10: =F8-F9 -> 20481.906 | G10: =G8-G9 -> 22939.735
A11: Capital Expenditure | B11: 6000 | C11: =C3*Assumptions!B22 -> 7750.402 | D11: =D3*Assumptions!B22 -> 8959.4647 | E11: =E3*Assumptions!B22 -> 10357.141 | F11: =F3*Assumptions!B22 -> 11599.998 | G11: =G3*Assumptions!B22 -> 12991.998 | I11: CORRECTED: was =B3*22% (projection formula). FY25A actual CapEx ₹6,000 Cr. Source: APSEZ FY25 Cash Flow Statement, BSE Filing. [Error 6]
A12: Change in Working Capital | B12: -500 | C12: =C3*Assumptions!B23 -> -1056.873 | D12: =D3*Assumptions!B23 -> -1221.7452 | E12: =E3*Assumptions!B23 -> -1412.3374 | F12: =F3*Assumptions!B23 -> -1581.8179 | G12: =G3*Assumptions!B23 -> -1771.6361 | I12: CORRECTED: was =B3*-3% (projection formula). FY25A actual ΔWC ₹-500 Cr. Source: APSEZ FY25 Cash Flow Statement, BSE Filing. [Error 6]
A13: Unlevered Free Cash Flow | B13: =B10+B7-B11-B12 -> 10576.7 | C13: =C10+C7-C11-C12 -> 12028.976 | D13: =D10+D7-D11-D12 -> 13905.496 | E13: =E10+E7-E11-E12 -> 16074.754 | F13: =F10+F7-F11-F12 -> 18003.724 | G13: =G10+G7-G11-G12 -> 20164.171
A16: DISCOUNTING & TERMINAL VALUE
A17: Discount Period (mid-year) | C17: 0.5 | D17: 1.5 | E17: 2.5 | F17: 3.5 | G17: 4.5
A18: Discount Factor | C18: =1/((1+Assumptions!B13)^C17) -> 0.94711744 | D18: =1/((1+Assumptions!B13)^D17) -> 0.84959411 | E18: =1/((1+Assumptions!B13)^E17) -> 0.76211263 | F18: =1/((1+Assumptions!B13)^F17) -> 0.68363899 | G18: =1/((1+Assumptions!B13)^G17) -> 0.61324566
A19: PV of UFCF | C19: =C13*C18 -> 11392.853 | D19: =D13*D18 -> 11814.028 | E19: =E13*E18 -> 12250.773 | F19: =F13*F18 -> 12308.048 | G19: =G13*G18 -> 12365.591
A21: Terminal Value (Gordon Growth) | B21: =(G13*(1+Assumptions!B24))/(Assumptions!B13-Assumptions!B24) -> 355809.75
A22: PV of Terminal Value | B22: =B21/(1+Assumptions!B13)^5 -> 206659.88 | I22: CORRECTED: was =B21/G18 (divided = inflated TV). Now =B21/(1+WACC)^5 for correct year-end discounting. [Errors 1 & New A]
A23: Sum of PV (FCF) | B23: =SUM(C19:G19) -> 60131.292
A24: Enterprise Value (₹ Cr) | B24: =B22+B23 -> 266791.17
A25: (+) Cash & Equivalents | B25: =Assumptions!B26 -> 4659
A26: (-) Total Debt | B26: =Assumptions!B27 -> 51621
A27: (-) Minority Interest | B27: =Assumptions!B28 -> 8500
A28: Equity Value (₹ Cr) | B28: =B24+B25-B26-B27 -> 211329.17
A29: Shares Outstanding (Cr) | B29: =Assumptions!B25 -> 216
A30: Implied Share Price (₹) | B30: =B28/B29 -> 978.37578
A31: Current Market Price (₹) | B31: 1344
A32: Upside / (Downside) | B32: =(B30-B31)/B31 -> -0.27204183

Sheet Sensitivity
A1: SENSITIVITY: IMPLIED SHARE PRICE (₹) — WACC × Terminal Growth Rate
A2: WACC \ TGR | C2: 4.5% | D2: 5.0% | E2: 5.5% | F2: 6.0% | G2: 6.5%
A4: 9.0% | C4: =(DCF!C13/(1+0.09)^0.5+DCF!D13/(1+0.09)^1.5+DCF!E13/(1+0.09)^2.5+DCF!F13/(1+0.09)^3.5+DCF!G13/(1+0.09)^4.5+(DCF!G13*(1+0.045)/(0.09-0.045))/(1+0.09)^5+Assumptions!B26-Assumptions!B27-Assumptions!B28)/Assumptions!B25 -> 1447.0891 | D4: =(DCF!C13/(1+0.09)^0.5+DCF!D13/(1+0.09)^1.5+DCF!E13/(1+0.09)^2.5+DCF!F13/(1+0.09)^3.5+DCF!G13/(1+0.09)^4.5+(DCF!G13*(1+0.05)/(0.09-0.05))/(1+0.09)^5+Assumptions!B26-Assumptions!B27-Assumptions!B28)/Assumptions!B25 -> 1630.7929 | E4: =(DCF!C13/(1+0.09)^0.5+DCF!D13/(1+0.09)^1.5+DCF!E13/(1+0.09)^2.5+DCF!F13/(1+0.09)^3.5+DCF!G13/(1+0.09)^4.5+(DCF!G13*(1+0.055)/(0.09-0.055))/(1+0.09)^5+Assumptions!B26-Assumptions!B27-Assumptions!B28)/Assumptions!B25 -> 1866.9835 | F4: =(DCF!C13/(1+0.09)^0.5+DCF!D13/(1+0.09)^1.5+DCF!E13/(1+0.09)^2.5+DCF!F13/(1+0.09)^3.5+DCF!G13/(1+0.09)^4.5+(DCF!G13*(1+0.06)/(0.09-0.06))/(1+0.09)^5+Assumptions!B26-Assumptions!B27-Assumptions!B28)/Assumptions!B25 -> 2181.9043 | G4: =(DCF!C13/(1+0.09)^0.5+DCF!D13/(1+0.09)^1.5+DCF!E13/(1+0.09)^2.5+DCF!F13/(1+0.09)^3.5+DCF!G13/(1+0.09)^4.5+(DCF!G13*(1+0.065)/(0.09-0.065))/(1+0.09)^5+Assumptions!B26-Assumptions!B27-Assumptions!B28)/Assumptions!B25 -> 2622.7934
A5: 9.5% | C5: =(DCF!C13/(1+0.095)^0.5+DCF!D13/(1+0.095)^1.5+DCF!E13/(1+0.095)^2.5+DCF!F13/(1+0.095)^3.5+DCF!G13/(1+0.095)^4.5+(DCF!G13*(1+0.045)/(0.095-0.045))/(1+0.095)^5+Assumptions!B26-Assumptions!B27-Assumptions!B28)/Assumptions!B25 -> 1274.043 | D5: =(DCF!C13/(1+0.095)^0.5+DCF!D13/(1+0.095)^1.5+DCF!E13/(1+0.095)^2.5+DCF!F13/(1+0.095)^3.5+DCF!G13/(1+0.095)^4.5+(DCF!G13*(1+0.05)/(0.095-0.05))/(1+0.095)^5+Assumptions!B26-Assumptions!B27-Assumptions!B28)/Assumptions!B25 -> 1418.3401 | E5: =(DCF!C13/(1+0.095)^0.5+DCF!D13/(1+0.095)^1.5+DCF!E13/(1+0.095)^2.5+DCF!F13/(1+0.095)^3.5+DCF!G13/(1+0.095)^4.5+(DCF!G13*(1+0.055)/(0.095-0.055))/(1+0.095)^5+Assumptions!B26-Assumptions!B27-Assumptions!B28)/Assumptions!B25 -> 1598.7115 | F5: =(DCF!C13/(1+0.095)^0.5+DCF!D13/(1+0.095)^1.5+DCF!E13/(1+0.095)^2.5+DCF!F13/(1+0.095)^3.5+DCF!G13/(1+0.095)^4.5+(DCF!G13*(1+0.06)/(0.095-0.06))/(1+0.095)^5+Assumptions!B26-Assumptions!B27-Assumptions!B28)/Assumptions!B25 -> 1830.6176 | G5: =(DCF!C13/(1+0.095)^0.5+DCF!D13/(1+0.095)^1.5+DCF!E13/(1+0.095)^2.5+DCF!F13/(1+0.095)^3.5+DCF!G13/(1+0.095)^4.5+(DCF!G13*(1+0.065)/(0.095-0.065))/(1+0.095)^5+Assumptions!B26-Assumptions!B27-Assumptions!B28)/Assumptions!B25 -> 2139.8257
A6: 10.0% | C6: =(DCF!C13/(1+0.1)^0.5+DCF!D13/(1+0.1)^1.5+DCF!E13/(1+0.1)^2.5+DCF!F13/(1+0.1)^3.5+DCF!G13/(1+0.1)^4.5+(DCF!G13*(1+0.045)/(0.1-0.045))/(1+0.1)^5+Assumptions!B26-Assumptions!B27-Assumptions!B28)/Assumptions!B25 -> 1132.6031 | D6: =(DCF!C13/(1+0.1)^0.5+DCF!D13/(1+0.1)^1.5+DCF!E13/(1+0.1)^2.5+DCF!F13/(1+0.1)^3.5+DCF!G13/(1+0.1)^4.5+(DCF!G13*(1+0.05)/(0.1-0.05))/(1+0.1)^5+Assumptions!B26-Assumptions!B27-Assumptions!B28)/Assumptions!B25 -> 1248.5324 | E6: =(DCF!C13/(1+0.1)^0.5+DCF!D13/(1+0.1)^1.5+DCF!E13/(1+0.1)^2.5+DCF!F13/(1+0.1)^3.5+DCF!G13/(1+0.1)^4.5+(DCF!G13*(1+0.055)/(0.1-0.055))/(1+0.1)^5+Assumptions!B26-Assumptions!B27-Assumptions!B28)/Assumptions!B25 -> 1390.2238 | F6: =(DCF!C13/(1+0.1)^0.5+DCF!D13/(1+0.1)^1.5+DCF!E13/(1+0.1)^2.5+DCF!F13/(1+0.1)^3.5+DCF!G13/(1+0.1)^4.5+(DCF!G13*(1+0.06)/(0.1-0.06))/(1+0.1)^5+Assumptions!B26-Assumptions!B27-Assumptions!B28)/Assumptions!B25 -> 1567.338 | G6: =(DCF!C13/(1+0.1)^0.5+DCF!D13/(1+0.1)^1.5+DCF!E13/(1+0.1)^2.5+DCF!F13/(1+0.1)^3.5+DCF!G13/(1+0.1)^4.5+(DCF!G13*(1+0.065)/(0.1-0.065))/(1+0.1)^5+Assumptions!B26-Assumptions!B27-Assumptions!B28)/Assumptions!B25 -> 1795.0563
A7: 10.5% | C7: =(DCF!C13/(1+0.105)^0.5+DCF!D13/(1+0.105)^1.5+DCF!E13/(1+0.105)^2.5+DCF!F13/(1+0.105)^3.5+DCF!G13/(1+0.105)^4.5+(DCF!G13*(1+0.045)/(0.105-0.045))/(1+0.105)^5+Assumptions!B26-Assumptions!B27-Assumptions!B28)/Assumptions!B25 -> 1014.8629 | D7: =(DCF!C13/(1+0.105)^0.5+DCF!D13/(1+0.105)^1.5+DCF!E13/(1+0.105)^2.5+DCF!F13/(1+0.105)^3.5+DCF!G13/(1+0.105)^4.5+(DCF!G13*(1+0.05)/(0.105-0.05))/(1+0.105)^5+Assumptions!B26-Assumptions!B27-Assumptions!B28)/Assumptions!B25 -> 1109.734 | E7: =(DCF!C13/(1+0.105)^0.5+DCF!D13/(1+0.105)^1.5+DCF!E13/(1+0.105)^2.5+DCF!F13/(1+0.105)^3.5+DCF!G13/(1+0.105)^4.5+(DCF!G13*(1+0.055)/(0.105-0.055))/(1+0.105)^5+Assumptions!B26-Assumptions!B27-Assumptions!B28)/Assumptions!B25 -> 1223.5792 | F7: =(DCF!C13/(1+0.105)^0.5+DCF!D13/(1+0.105)^1.5+DCF!E13/(1+0.105)^2.5+DCF!F13/(1+0.105)^3.5+DCF!G13/(1+0.105)^4.5+(DCF!G13*(1+0.06)/(0.105-0.06))/(1+0.105)^5+Assumptions!B26-Assumptions!B27-Assumptions!B28)/Assumptions!B25 -> 1362.7234 | G7: =(DCF!C13/(1+0.105)^0.5+DCF!D13/(1+0.105)^1.5+DCF!E13/(1+0.105)^2.5+DCF!F13/(1+0.105)^3.5+DCF!G13/(1+0.105)^4.5+(DCF!G13*(1+0.065)/(0.105-0.065))/(1+0.105)^5+Assumptions!B26-Assumptions!B27-Assumptions!B28)/Assumptions!B25 -> 1536.6536
A8: 11.0% | C8: =(DCF!C13/(1+0.11)^0.5+DCF!D13/(1+0.11)^1.5+DCF!E13/(1+0.11)^2.5+DCF!F13/(1+0.11)^3.5+DCF!G13/(1+0.11)^4.5+(DCF!G13*(1+0.045)/(0.11-0.045))/(1+0.11)^5+Assumptions!B26-Assumptions!B27-Assumptions!B28)/Assumptions!B25 -> 915.34883 | D8: =(DCF!C13/(1+0.11)^0.5+DCF!D13/(1+0.11)^1.5+DCF!E13/(1+0.11)^2.5+DCF!F13/(1+0.11)^3.5+DCF!G13/(1+0.11)^4.5+(DCF!G13*(1+0.05)/(0.11-0.05))/(1+0.11)^5+Assumptions!B26-Assumptions!B27-Assumptions!B28)/Assumptions!B25 -> 994.18765 | E8: =(DCF!C13/(1+0.11)^0.5+DCF!D13/(1+0.11)^1.5+DCF!E13/(1+0.11)^2.5+DCF!F13/(1+0.11)^3.5+DCF!G13/(1+0.11)^4.5+(DCF!G13*(1+0.055)/(0.11-0.055))/(1+0.11)^5+Assumptions!B26-Assumptions!B27-Assumptions!B28)/Assumptions!B25 -> 1087.3608 | F8: =(DCF!C13/(1+0.11)^0.5+DCF!D13/(1+0.11)^1.5+DCF!E13/(1+0.11)^2.5+DCF!F13/(1+0.11)^3.5+DCF!G13/(1+0.11)^4.5+(DCF!G13*(1+0.06)/(0.11-0.06))/(1+0.11)^5+Assumptions!B26-Assumptions!B27-Assumptions!B28)/Assumptions!B25 -> 1199.1686 | G8: =(DCF!C13/(1+0.11)^0.5+DCF!D13/(1+0.11)^1.5+DCF!E13/(1+0.11)^2.5+DCF!F13/(1+0.11)^3.5+DCF!G13/(1+0.11)^4.5+(DCF!G13*(1+0.065)/(0.11-0.065))/(1+0.11)^5+Assumptions!B26-Assumptions!B27-Assumptions!B28)/Assumptions!B25 -> 1335.8225
A9: 11.5% | C9: =(DCF!C13/(1+0.115)^0.5+DCF!D13/(1+0.115)^1.5+DCF!E13/(1+0.115)^2.5+DCF!F13/(1+0.115)^3.5+DCF!G13/(1+0.115)^4.5+(DCF!G13*(1+0.045)/(0.115-0.045))/(1+0.115)^5+Assumptions!B26-Assumptions!B27-Assumptions!B28)/Assumptions!B25 -> 830.15126 | D9: =(DCF!C13/(1+0.115)^0.5+DCF!D13/(1+0.115)^1.5+DCF!E13/(1+0.115)^2.5+DCF!F13/(1+0.115)^3.5+DCF!G13/(1+0.115)^4.5+(DCF!G13*(1+0.05)/(0.115-0.05))/(1+0.115)^5+Assumptions!B26-Assumptions!B27-Assumptions!B28)/Assumptions!B25 -> 896.52339 | E9: =(DCF!C13/(1+0.115)^0.5+DCF!D13/(1+0.115)^1.5+DCF!E13/(1+0.115)^2.5+DCF!F13/(1+0.115)^3.5+DCF!G13/(1+0.115)^4.5+(DCF!G13*(1+0.055)/(0.115-0.055))/(1+0.115)^5+Assumptions!B26-Assumptions!B27-Assumptions!B28)/Assumptions!B25 -> 973.95755 | F9: =(DCF!C13/(1+0.115)^0.5+DCF!D13/(1+0.115)^1.5+DCF!E13/(1+0.115)^2.5+DCF!F13/(1+0.115)^3.5+DCF!G13/(1+0.115)^4.5+(DCF!G13*(1+0.06)/(0.115-0.06))/(1+0.115)^5+Assumptions!B26-Assumptions!B27-Assumptions!B28)/Assumptions!B25 -> 1065.4706 | G9: =(DCF!C13/(1+0.115)^0.5+DCF!D13/(1+0.115)^1.5+DCF!E13/(1+0.115)^2.5+DCF!F13/(1+0.115)^3.5+DCF!G13/(1+0.115)^4.5+(DCF!G13*(1+0.065)/(0.115-0.065))/(1+0.115)^5+Assumptions!B26-Assumptions!B27-Assumptions!B28)/Assumptions!B25 -> 1175.2863
A10: Note: Yellow = base case (WACC 11.5%, TGR 5.5%) — model WACC = 11.48%; 12.0% row in row 11 below
A11: 12.0% | C11: =(DCF!C13/(1+0.12)^0.5+DCF!D13/(1+0.12)^1.5+DCF!E13/(1+0.12)^2.5+DCF!F13/(1+0.12)^3.5+DCF!G13/(1+0.12)^4.5+(DCF!G13*(1+0.045)/(0.12-0.045))/(1+0.12)^5+Assumptions!B26-Assumptions!B27-Assumptions!B28)/Assumptions!B25 -> 756.4034 | D11: =(DCF!C13/(1+0.12)^0.5+DCF!D13/(1+0.12)^1.5+DCF!E13/(1+0.12)^2.5+DCF!F13/(1+0.12)^3.5+DCF!G13/(1+0.12)^4.5+(DCF!G13*(1+0.05)/(0.12-0.05))/(1+0.12)^5+Assumptions!B26-Assumptions!B27-Assumptions!B28)/Assumptions!B25 -> 812.90558 | E11: =(DCF!C13/(1+0.12)^0.5+DCF!D13/(1+0.12)^1.5+DCF!E13/(1+0.12)^2.5+DCF!F13/(1+0.12)^3.5+DCF!G13/(1+0.12)^4.5+(DCF!G13*(1+0.055)/(0.12-0.055))/(1+0.12)^5+Assumptions!B26-Assumptions!B27-Assumptions!B28)/Assumptions!B25 -> 878.10041 | F11: =(DCF!C13/(1+0.12)^0.5+DCF!D13/(1+0.12)^1.5+DCF!E13/(1+0.12)^2.5+DCF!F13/(1+0.12)^3.5+DCF!G13/(1+0.12)^4.5+(DCF!G13*(1+0.06)/(0.12-0.06))/(1+0.12)^5+Assumptions!B26-Assumptions!B27-Assumptions!B28)/Assumptions!B25 -> 954.16104 | G11: =(DCF!C13/(1+0.12)^0.5+DCF!D13/(1+0.12)^1.5+DCF!E13/(1+0.12)^2.5+DCF!F13/(1+0.12)^3.5+DCF!G13/(1+0.12)^4.5+(DCF!G13*(1+0.065)/(0.12-0.065))/(1+0.12)^5+Assumptions!B26-Assumptions!B27-Assumptions!B28)/Assumptions!B25 -> 1044.0509
